m3s_grpc/__init__.py
m3s_grpc/m3s_pb2.py
m3s_grpc/m3s_pb2_grpc.py
mmpredict_grpc/__init__.py
mmpredict_grpc/mmpredict_pb2.py
mmpredict_grpc/mmpredict_pb2_grpc.py
mm_predict_grpc-0.2.dist-info/METADATA
mm_predict_grpc-0.2.dist-info/WHEEL
mm_predict_grpc-0.2.dist-info/top_level.txt
mm_predict_grpc-0.2.dist-info/RECORD
