Metadata-Version: 2.1
Name: mm-predict-grpc
Version: 0.2
Summary: gRPC library for client & server interactions with the MM Predict M3S Model execution container.
Home-page: http://github.com/massmutual/predict-m3s/
Author: Jonathan Ellenberger
Author-email: jellenberger@massmutual.com
License: UNKNOWN
Platform: UNKNOWN
Classifier: Development Status :: 3 - Alpha
Classifier: Environment :: Web Environment
Classifier: Intended Audience :: Developers
Classifier: Natural Language :: English
Classifier: Operating System :: OS Independent
Classifier: Programming Language :: Python
Classifier: Programming Language :: Python :: 3
Classifier: Programming Language :: Python :: 3.4
Requires-Dist: grpcio (==1.19.0)
Requires-Dist: grpcio-tools (==1.19.0)
Requires-Dist: googleapis-common-protos (==1.5.5)
